webpilot/__init__.py
webpilot/backends/async_pilot.py
webpilot/backends/playwright_pilot.py
webpilot/backends/selenium.py
webpilot/cicd/template_generator.py
webpilot/cli.py
webpilot/cloud/cloud_browser.py
webpilot/core.py
webpilot/features/devops.py
webpilot/features/vision.py
webpilot/integrations/cicd.py
webpilot/mcp/__init__.py
webpilot/mcp/cloud_manager.py
webpilot/mcp/error_handler.py
webpilot/mcp/performance.py
webpilot/mcp/resources.py
webpilot/mcp/run_server.py
webpilot/mcp/server.py
webpilot/mcp/tools.py
webpilot/mcp/tools_extended.py
webpilot/ml/test_generator.py
webpilot/monitoring/dashboard.py
webpilot/utils/__init__.py
webpilot/utils/error_handler.py
webpilot/utils/logging_config.py
webpilot/utils/reporter.py
webpilot/utils/smart_wait.py
claude_webpilot-1.3.0.dist-info/LICENSE
claude_webpilot-1.3.0.dist-info/METADATA
claude_webpilot-1.3.0.dist-info/WHEEL
claude_webpilot-1.3.0.dist-info/entry_points.txt
claude_webpilot-1.3.0.dist-info/RECORD
