Metadata-Version: 2.3
Name: claude-webpilot
Version: 1.3.0
Summary: Professional Web Automation and Testing Framework with 60+ MCP Tools, Cloud Platform Support, and Performance Optimization
License: MIT
Keywords: web automation,testing,selenium,playwright,devops,ci/cd,machine learning,test generation,cloud testing,accessibility testing,performance testing,mcp,model context protocol,ai assistant integration
Author: WebPilot Contributors
Maintainer: WebPilot Team
Maintainer-email: webpilot@example.com
Requires-Python: >=3.10,<4.0
Classifier: Development Status :: 4 - Beta
Classifier: Framework :: Pytest
Classifier: Intended Audience :: Developers
Classifier: License :: OSI Approved :: MIT License
Classifier: Operating System :: OS Independent
Classifier: Programming Language :: Python :: 3
Classifier: Programming Language :: Python :: 3.10
Classifier: Programming Language :: Python :: 3.11
Classifier: Programming Language :: Python :: 3.12
Classifier: Programming Language :: Python :: 3.13
Classifier: Programming Language :: Python :: 3.9
Classifier: Topic :: Internet :: WWW/HTTP :: Browsers
Classifier: Topic :: Software Development :: Quality Assurance
Classifier: Topic :: Software Development :: Testing
Provides-Extra: all
Provides-Extra: vision
Requires-Dist: aiohttp (>=3.12.0,<4.0.0)
Requires-Dist: beautifulsoup4 (>=4.13.0,<5.0.0)
Requires-Dist: click (>=8.1.0,<9.0.0)
Requires-Dist: numpy (>=1.26.0) ; extra == "vision" or extra == "all"
Requires-Dist: opencv-python (>=4.12.0,<5.0.0) ; extra == "vision" or extra == "all"
Requires-Dist: pillow (>=10.0.0,<11.0.0)
Requires-Dist: playwright (>=1.55.0,<2.0.0)
Requires-Dist: pytesseract (>=0.3.10,<0.4.0) ; extra == "vision" or extra == "all"
Requires-Dist: pyyaml (>=6.0.2,<7.0.0)
Requires-Dist: requests (>=2.31.0,<3.0.0)
Requires-Dist: scikit-learn (>=1.7.2,<2.0.0)
Requires-Dist: selenium (>=4.29.0,<5.0.0)
Project-URL: Documentation, https://luminous-dynamics.github.io/webpilot/
Project-URL: Homepage, https://github.com/Luminous-Dynamics/webpilot
Project-URL: Repository, https://github.com/Luminous-Dynamics/webpilot
